sinapsis_huggingface-0.2.14.dist-info/licenses/LICENSE
sinapsis_huggingface_diffusers/src/sinapsis_huggingface_diffusers/__init__.py
sinapsis_huggingface_diffusers/src/sinapsis_huggingface_diffusers/helpers/__init__.py
sinapsis_huggingface_diffusers/src/sinapsis_huggingface_diffusers/helpers/tags.py
sinapsis_huggingface_diffusers/src/sinapsis_huggingface_diffusers/templates/__init__.py
sinapsis_huggingface_diffusers/src/sinapsis_huggingface_diffusers/templates/base_diffusers.py
sinapsis_huggingface_diffusers/src/sinapsis_huggingface_diffusers/templates/image_to_image_diffusers.py
sinapsis_huggingface_diffusers/src/sinapsis_huggingface_diffusers/templates/image_to_video_gen_xl_diffusers.py
sinapsis_huggingface_diffusers/src/sinapsis_huggingface_diffusers/templates/inpainting_diffusers.py
sinapsis_huggingface_diffusers/src/sinapsis_huggingface_diffusers/templates/text_to_image_diffusers.py
sinapsis_huggingface_embeddings/src/sinapsis_huggingface_embeddings/__init__.py
sinapsis_huggingface_embeddings/src/sinapsis_huggingface_embeddings/helpers/__init__.py
sinapsis_huggingface_embeddings/src/sinapsis_huggingface_embeddings/helpers/tags.py
sinapsis_huggingface_embeddings/src/sinapsis_huggingface_embeddings/templates/__init__.py
sinapsis_huggingface_embeddings/src/sinapsis_huggingface_embeddings/templates/hugging_face_embedding_extractor.py
sinapsis_huggingface_embeddings/src/sinapsis_huggingface_embeddings/templates/speaker_embedding_from_audio.py
sinapsis_huggingface_grounding_dino/src/sinapsis_huggingface_grounding_dino/__init__.py
sinapsis_huggingface_grounding_dino/src/sinapsis_huggingface_grounding_dino/helpers/__init__.py
sinapsis_huggingface_grounding_dino/src/sinapsis_huggingface_grounding_dino/helpers/grounding_dino_keys.py
sinapsis_huggingface_grounding_dino/src/sinapsis_huggingface_grounding_dino/helpers/tags.py
sinapsis_huggingface_grounding_dino/src/sinapsis_huggingface_grounding_dino/templates/__init__.py
sinapsis_huggingface_grounding_dino/src/sinapsis_huggingface_grounding_dino/templates/grounding_dino.py
sinapsis_huggingface-0.2.14.dist-info/METADATA
sinapsis_huggingface-0.2.14.dist-info/WHEEL
sinapsis_huggingface-0.2.14.dist-info/top_level.txt
sinapsis_huggingface-0.2.14.dist-info/RECORD
