Metadata-Version: 2.4
Name: sinapsis-huggingface
Version: 0.2.14
Summary: Package for HuggingFace-based templates
Author-email: SinapsisAI <dev@sinapsis.tech>
Project-URL: Homepage, https://sinapsis.tech
Project-URL: Documentation, https://docs.sinapsis.tech/docs
Project-URL: Tutorials, https://docs.sinapsis.tech/tutorials
Project-URL: Repository, https://github.com/Sinapsis-AI/sinapsis-huggingface.git
Requires-Python: >=3.10
License-File: LICENSE
Requires-Dist: sinapsis>=0.1.1
Provides-Extra: gradio-app
Requires-Dist: sinapsis-data-readers[opencv]>=0.1.0; extra == "gradio-app"
Requires-Dist: sinapsis-data-visualization[visualization-matplotlib]>=0.1.0; extra == "gradio-app"
Requires-Dist: sinapsis-huggingface-diffusers[all]; extra == "gradio-app"
Requires-Dist: sinapsis-huggingface-grounding-dino; extra == "gradio-app"
Requires-Dist: sinapsis-ultralytics>=0.1.0; extra == "gradio-app"
Requires-Dist: sinapsis[webapp]>=0.2.7; extra == "gradio-app"
Provides-Extra: all
Requires-Dist: sinapsis-huggingface-diffusers[all]; extra == "all"
Requires-Dist: sinapsis-huggingface-embeddings; extra == "all"
Requires-Dist: sinapsis-huggingface-grounding-dino; extra == "all"
Requires-Dist: sinapsis-huggingface-transformers; extra == "all"
Requires-Dist: sinapsis-huggingface-hub[all]; extra == "all"
Requires-Dist: sinapsis-huggingface[gradio-app,sinapsis-data-writers]; extra == "all"
Provides-Extra: sinapsis-data-writers
Requires-Dist: sinapsis-data-writers>=0.1.0; extra == "sinapsis-data-writers"
Dynamic: license-file
